market_data_core/__init__.py
market_data_core/_models.py
market_data_core/cli.py
market_data_core/config.py
market_data_core/errors.py
market_data_core/protocols.py
market_data_core/py.typed
market_data_core/settings.py
market_data_core/typing.py
market_data_core/adapters/__init__.py
market_data_core/adapters/base.py
market_data_core/adapters/ibkr_adapter.py
market_data_core/adapters/ibkr_options.py
market_data_core/adapters/ibkr_streams.py
market_data_core/configs/__init__.py
market_data_core/configs/loader.py
market_data_core/configs/model.py
market_data_core/contracts/__init__.py
market_data_core/contracts/compat.py
market_data_core/contracts/registry.py
market_data_core/events/__init__.py
market_data_core/events/envelope.py
market_data_core/events/factory.py
market_data_core/events/observability.py
market_data_core/events/protocols.py
market_data_core/events/security.py
market_data_core/events/adapters/__init__.py
market_data_core/events/adapters/inmem.py
market_data_core/events/adapters/redis_streams.py
market_data_core/events/codecs/__init__.py
market_data_core/events/codecs/json_codec.py
market_data_core/federation/__init__.py
market_data_core/federation/status.py
market_data_core/federation/types.py
market_data_core/models/__init__.py
market_data_core/models/contracts.py
market_data_core/models/errors.py
market_data_core/models/health.py
market_data_core/models/market_data.py
market_data_core/models/options.py
market_data_core/models/portfolio.py
market_data_core/models/registry.py
market_data_core/providers/__init__.py
market_data_core/providers/ibkr.py
market_data_core/providers/synthetic.py
market_data_core/registry/__init__.py
market_data_core/registry/protocols.py
market_data_core/registry/types.py
market_data_core/registry/utils.py
market_data_core/runtime/__init__.py
market_data_core/runtime/provider_protocol.py
market_data_core/runtime/registry.py
market_data_core/schemas/__init__.py
market_data_core/schemas/models.py
market_data_core-1.4.61.dist-info/METADATA
market_data_core-1.4.61.dist-info/WHEEL
market_data_core-1.4.61.dist-info/entry_points.txt
market_data_core-1.4.61.dist-info/top_level.txt
market_data_core-1.4.61.dist-info/RECORD
