Metadata-Version: 2.4
Name: market-data-core
Version: 1.4.61
Summary: Core contracts (protocols, models, errors, settings, telemetry, federation) for market data systems.
Author: Matt
License: MIT
Keywords: market-data,schemas,contracts,telemetry
Classifier: Programming Language :: Python :: 3
Classifier: Programming Language :: Python :: 3.11
Classifier: Typing :: Typed
Requires-Python: >=3.11
Requires-Dist: pydantic<3,>=2.7
Requires-Dist: python-dotenv<2,>=1.0
Requires-Dist: pyyaml<7,>=6.0
Requires-Dist: click<9,>=8.1
Provides-Extra: dev
Requires-Dist: pytest<9,>=8.2; extra == "dev"
Requires-Dist: pytest-asyncio<1,>=0.23; extra == "dev"
Requires-Dist: ruff<1,>=0.6; extra == "dev"
Requires-Dist: black<25,>=24.8; extra == "dev"
Requires-Dist: mypy<2,>=1.11; extra == "dev"
Requires-Dist: types-PyYAML<7,>=6.0; extra == "dev"
Requires-Dist: build<2,>=1.0; extra == "dev"
Provides-Extra: bus
Requires-Dist: redis<6,>=5.0; extra == "bus"
Provides-Extra: api
Requires-Dist: fastapi<0.116,>=0.115; extra == "api"
Requires-Dist: uvicorn[standard]<0.33,>=0.30; extra == "api"
Requires-Dist: httpx<0.29,>=0.28; extra == "api"
Requires-Dist: websockets<13,>=12; extra == "api"
Provides-Extra: observability
Requires-Dist: tenacity<9,>=8.2; extra == "observability"
Requires-Dist: loguru<0.8,>=0.7; extra == "observability"
Requires-Dist: prometheus-client<0.21,>=0.20; extra == "observability"
Requires-Dist: orjson<4,>=3.10; extra == "observability"
Provides-Extra: pandas
Requires-Dist: pandas<3,>=2.2.2; extra == "pandas"
Requires-Dist: orjson<4,>=3.10; extra == "pandas"
Provides-Extra: ibkr
Requires-Dist: ib_async>=1.0.0; extra == "ibkr"
Provides-Extra: compat
Requires-Dist: fastapi<0.116,>=0.115; extra == "compat"
Requires-Dist: uvicorn[standard]<0.33,>=0.30; extra == "compat"
Requires-Dist: httpx<0.29,>=0.28; extra == "compat"
Requires-Dist: websockets<13,>=12; extra == "compat"
Requires-Dist: tenacity<9,>=8.2; extra == "compat"
Requires-Dist: loguru<0.8,>=0.7; extra == "compat"
Requires-Dist: prometheus-client<0.21,>=0.20; extra == "compat"
Requires-Dist: orjson<4,>=3.10; extra == "compat"
Requires-Dist: pandas<3,>=2.2.2; extra == "compat"
Requires-Dist: ib_async>=1.0.0; extra == "compat"
Requires-Dist: redis<6,>=5.0; extra == "compat"
